arcx/__init__.py
arcx/conf/__init__.py
arcx/conf/global_settings.py
arcx/conf/reader.py
arcx/core/__init__.py
arcx/core/cleaner/__init__.py
arcx/core/cleaner/model.py
arcx/core/cleaner/service.py
arcx/core/md5.py
arcx/core/safe_rm/__init__.py
arcx/core/safe_rm/service.py
arcx/core/utils.py
arcx/management/__init__.py
arcx/management/cli.py
arcx/utils/__init__.py
arcx/utils/log.py
arcx/utils/module_loading.py
arcx-0.2.1.dist-info/LICENSE
arcx-0.2.1.dist-info/METADATA
arcx-0.2.1.dist-info/WHEEL
arcx-0.2.1.dist-info/entry_points.txt
arcx-0.2.1.dist-info/RECORD
